README.md
setup.py
replacex/__init__.py
replacex.egg-info/PKG-INFO
replacex.egg-info/SOURCES.txt
replacex.egg-info/dependency_links.txt
replacex.egg-info/entry_points.txt
replacex.egg-info/top_level.txt