Metadata-Version: 1.0
Name: replacex
Version: 1.2.0
Summary: Replace string (regular expression) for files in current folder
Home-page: https://github.com/leonsim/replacex
Author: 1e0n
Author-email: i@leons.im
License: MIT
Keywords: replace all string regular expression folder
Platform: UNKNOWN
